{
    "eye.svg": 61440,
    "facebook.svg": 61441,
    "heart.svg": 61442,
    "search.svg": 61443,
    "section.svg": 61444,
    "share.svg": 61445,
    "spotify.svg": 61446,
    "spotifyLogo.svg": 61447,
    "tweter.svg": 61448,
    "user.svg": 61449,
    "youtube.svg": 61450,
    "youtubeLogo.svg": 61451,
    "twitter.svg": 61452,
    "clock.svg": 61453,
    "info.svg": 61454,
    "heartLike.svg": 61455,
    "link.svg": 61456,
    "message.svg": 61457,
    "print.svg": 61458,
    "whatsapp.svg": 61459
}